<BackupInst xmlns="http://www.microsoft.com/GroupPolicy/GPOOperations/Manifest"><GPOGuid><![CDATA[{AFBBF7B6-2F19-427B-A1D5-9EA4C69B30A5}]]></GPOGuid><GPODomain><![CDATA[security.local]]></GPODomain><GPODomainGuid><![CDATA[{2b127034-e676-4f54-b03a-e700e3004cb0}]]></GPODomainGuid><GPODomainController><![CDATA[GPOSrv2016.security.local]]></GPODomainController><BackupTime><![CDATA[2019-01-24T19:42:45]]></BackupTime><ID><![CDATA[{B5E8F89E-79D7-4682-AC39-77A3564C4B3B}]]></ID><Comment><![CDATA[]]></Comment><GPODisplayName><![CDATA[DoD Windows 10 STIG Computer v1r16]]></GPODisplayName></BackupInst>
